surrogates_interface/__init__.py
surrogates_interface/domains.py
surrogates_interface/openmdao.py
surrogates_interface/surrogates.py
surrogates_interface/transformers.py
surrogates_interface-4.3.3.dist-info/METADATA
surrogates_interface-4.3.3.dist-info/WHEEL
surrogates_interface-4.3.3.dist-info/RECORD
